valorant/__init__.py
valorant/client.py
valorant/enums.py
valorant/errors.py
valorant/http.py
valorant/py.typed
valorant/utils.py
valorant/models/__init__.py
valorant/models/agents.py
valorant/models/base.py
valorant/models/buddies.py
valorant/models/bundles.py
valorant/models/ceremonies.py
valorant/models/competitive_tiers.py
valorant/models/content_tiers.py
valorant/models/contracts.py
valorant/models/currencies.py
valorant/models/events.py
valorant/models/flex.py
valorant/models/game_modes.py
valorant/models/gear.py
valorant/models/level_borders.py
valorant/models/localization.py
valorant/models/maps.py
valorant/models/missions.py
valorant/models/player_cards.py
valorant/models/player_titles.py
valorant/models/seasons.py
valorant/models/sprays.py
valorant/models/themes.py
valorant/models/version.py
valorant/models/weapons.py
valorant_py-2.3.1.dist-info/licenses/LICENSE
valorant_py-2.3.1.dist-info/METADATA
valorant_py-2.3.1.dist-info/WHEEL
valorant_py-2.3.1.dist-info/top_level.txt
valorant_py-2.3.1.dist-info/RECORD
