Metadata-Version: 2.4
Name: valorant.py
Version: 2.3.1
Summary: An API wrapper for Valorant API written in Python.
Author-email: STACiA <stacia.dev@gmail.com>
Project-URL: homepage, https://github.com/staciax/valorant
Project-URL: repository, https://github.com/staciax/valorant
Project-URL: issues, https://github.com/staciax/valorant/issues
Classifier: Intended Audience :: Developers
Classifier: License :: OSI Approved :: MIT License
Classifier: Operating System :: OS Independent
Classifier: Programming Language :: Python :: 3
Classifier: Programming Language :: Python
Classifier: Development Status :: 4 - Beta
Classifier: Typing :: Typed
Classifier: Framework :: AsyncIO
Classifier: Programming Language :: Python :: 3 :: Only
Classifier: Programming Language :: Python :: 3.10
Classifier: Programming Language :: Python :: 3.11
Classifier: Programming Language :: Python :: 3.12
Classifier: Programming Language :: Python :: 3.13
Classifier: Programming Language :: Python :: 3.14
Classifier: Topic :: Internet
Classifier: Topic :: Software Development :: Libraries :: Python Modules
Classifier: Topic :: Internet :: WWW/HTTP
Requires-Python: >=3.10
License-File: LICENSE
Requires-Dist: aiohttp<4.0,>=3.11
Requires-Dist: pydantic<3.0,>2.0
Requires-Dist: aiohttp-client-cache[sqlite]<1.0,>=0.14.2
Requires-Dist: pydantic-extra-types<3.0,>=2.10.6
Provides-Extra: speed
Requires-Dist: msgspec<1.0,>=0.19.0; extra == "speed"
Dynamic: license-file
